gaussianblur/__init__.py
gaussianblur/_dummy.cpython-311-x86_64-linux-gnu.so
gaussianblur/gaussianblur.cpython-311-x86_64-linux-gnu.so
gaussianblur/libGaussianblur.so
gaussianblur-1.1.2.dist-info/METADATA
gaussianblur-1.1.2.dist-info/WHEEL
gaussianblur-1.1.2.dist-info/top_level.txt
gaussianblur-1.1.2.dist-info/RECORD
gaussianblur-1.1.2.dist-info/licenses/LICENSE
