Metadata-Version: 2.4
Name: gaussianblur
Version: 1.1.2
Summary: A Python package to apply a super fast Gaussian blur through Fast Fourier Transform
Author-email: Michele Renzullo <renzullo@pm.me>
License-Expression: Apache-2.0
Project-URL: Homepage, https://github.com/michelerenzullo/LibGaussianBlur
Project-URL: Issues, https://github.com/michelerenzullo/LibGaussianBlur/issues
Keywords: gaussian blur,blur,tiles,image processing,convolution,fast fourier transform,FFT,python,bindings,C++,scientific,engineering
Classifier: Development Status :: 5 - Production/Stable
Classifier: Programming Language :: Python :: 3
Classifier: Programming Language :: Python :: 3.11
Classifier: Programming Language :: Python :: 3.12
Classifier: Programming Language :: Python :: 3.13
Classifier: Programming Language :: Python :: Implementation :: CPython
Classifier: Programming Language :: C++
Classifier: Operating System :: MacOS
Classifier: Operating System :: POSIX :: Linux
Classifier: Operating System :: Unix
Classifier: Topic :: Scientific/Engineering
Classifier: Topic :: Scientific/Engineering :: Image Processing
Requires-Python: >=3.11
License-File: LICENSE
Dynamic: license-file
